{
  "version": "0.3.1",
  "description": "BLS Snap",
  "proposedName": "@aquiladev/bls-snap",
  "repository": {
    "type": "git",
    "url": "https://github.com/aquiladev/bls-snap.git"
  },
  "source": {
    "shasum": "C7TlcF1PAaXMhYD1vgz5CoOzL6qES9BceUthCDs3zBs=",
    "location": {
      "npm": {
        "filePath": "dist/bundle.js",
        "iconPath": "images/icon.svg",
        "packageName": "@aquiladev/bls-snap",
        "registry": "https://registry.npmjs.org/"
      }
    }
  },
  "initialPermissions": {
    "snap_manageState": {},
    "snap_getBip44Entropy": [
      {
        "coinType": 9001
      }
    ],
    "endowment:network-access": {},
    "endowment:rpc": {
      "snaps": true,
      "dapps": true
    },
    "endowment:webassembly": {}
  },
  "manifestVersion": "0.1"
}
